dataset_utils/__init__.py
dataset_utils/buffered_writer.py
dataset_utils/counters.py
dataset_utils/dict_cache.py
dataset_utils/kv.py
dataset_utils/score_cache.py
dataset_utils/sqlite.py
dataset_utils-0.0.48.dist-info/LICENSE
dataset_utils-0.0.48.dist-info/METADATA
dataset_utils-0.0.48.dist-info/WHEEL
dataset_utils-0.0.48.dist-info/top_level.txt
dataset_utils-0.0.48.dist-info/RECORD
